adacut/__init__.py
adacut/adacut.py
adacut-1.1.dist-info/METADATA
adacut-1.1.dist-info/WHEEL
adacut-1.1.dist-info/entry_points.txt
adacut-1.1.dist-info/top_level.txt
adacut-1.1.dist-info/RECORD
