Metadata-Version: 2.1
Name: adacut
Version: 1.1
